{"nodes": [{"id": "readme", "label": "Neoliva Dental Clinic Dashboard", "file_type": "document", "source_file": "README.md"}, {"id": "src_services", "label": "Service Layer", "file_type": "concept", "source_file": "README.md"}, {"id": "src_repositories", "label": "Repository Layer", "file_type": "concept", "source_file": "README.md"}], "edges": [{"source": "src_config_di", "target": "src_services", "relation": "references", "confidence": "EXTRACTED", "confidence_score": 1.0, "source_file": "README.md"}, {"source": "src_config_di", "target": "src_repositories", "relation": "references", "confidence": "EXTRACTED", "confidence_score": 1.0, "source_file": "README.md"}, {"source": "src_services", "target": "src_repositories", "relation": "calls", "confidence": "EXTRACTED", "confidence_score": 1.0, "source_file": "README.md"}, {"source": "src_lib_prisma", "target": "src_repositories", "relation": "references", "confidence": "INFERRED", "confidence_score": 0.9, "source_file": "README.md"}, {"source": "src_lib_rbac_guard", "target": "src_lib_rbac", "relation": "conceptually_related_to", "confidence": "EXTRACTED", "confidence_score": 1.0, "source_file": "README.md"}, {"source": "src_proxy", "target": "src_lib_prisma", "relation": "references", "confidence": "INFERRED", "confidence_score": 0.8, "source_file": "README.md"}], "hyperedges": [{"id": "security_isolation_flow", "label": "Multi-Tenant Security Flow", "nodes": ["src_proxy", "src_lib_prisma", "src_lib_rbac_guard"], "relation": "participate_in", "confidence": "EXTRACTED", "confidence_score": 0.95, "source_file": "README.md"}, {"id": "decoupled_architecture", "label": "Decoupled Layered Architecture", "nodes": ["src_config_di", "src_services", "src_repositories", "src_lib_prisma"], "relation": "form", "confidence": "EXTRACTED", "confidence_score": 1.0, "source_file": "README.md"}]}